{
 "files": [
  {
   "name": ".",
   "ftype": "dir",
   "chksum_type": null,
   "chksum_sha256": null,
   "format": 1
  },
  {
   "name": "README.md",
   "ftype": "file",
   "chksum_type": "sha256",
   "chksum_sha256": "215b15d7d11669081c8185351b82ea813284998155c6ffd68fc3766aefca16a3",
   "format": 1
  },
  {
   "name": "docs",
   "ftype": "dir",
   "chksum_type": null,
   "chksum_sha256": null,
   "format": 1
  },
  {
   "name": "plugins",
   "ftype": "dir",
   "chksum_type": null,
   "chksum_sha256": null,
   "format": 1
  },
  {
   "name": "plugins/README.md",
   "ftype": "file",
   "chksum_type": "sha256",
   "chksum_sha256": "23e9939164cad964c2338b8059e4d3def72eef9523e32594503efd50960fcae4",
   "format": 1
  },
  {
   "name": "plugins/modules",
   "ftype": "dir",
   "chksum_type": null,
   "chksum_sha256": null,
   "format": 1
  },
  {
   "name": "plugins/modules/myping.py",
   "ftype": "file",
   "chksum_type": "sha256",
   "chksum_sha256": "621293a2452594ba3953e708dffce2a6d596fd4d7f3fccb39bfc8cab9551dfc6",
   "format": 1
  },
  {
   "name": "plugins/lookup",
   "ftype": "dir",
   "chksum_type": null,
   "chksum_sha256": null,
   "format": 1
  },
  {
   "name": "plugins/lookup/list.py",
   "ftype": "file",
   "chksum_type": "sha256",
   "chksum_sha256": "ec1ca5c9395276669f88c5c2546ec3230a85d88e670220e3f68b779c4febdce9",
   "format": 1
  },
  {
   "name": "roles",
   "ftype": "dir",
   "chksum_type": null,
   "chksum_sha256": null,
   "format": 1
  },
  {
   "name": "roles/external",
   "ftype": "dir",
   "chksum_type": null,
   "chksum_sha256": null,
   "format": 1
  },
  {
   "name": "roles/external/files",
   "ftype": "dir",
   "chksum_type": null,
   "chksum_sha256": null,
   "format": 1
  },
  {
   "name": "roles/external/handlers",
   "ftype": "dir",
   "chksum_type": null,
   "chksum_sha256": null,
   "format": 1
  },
  {
   "name": "roles/external/handlers/main.yml",
   "ftype": "file",
   "chksum_type": "sha256",
   "chksum_sha256": "92ce4a73287d32de461260173c25b81136717213efcde9df2981cfe4865c7917",
   "format": 1
  },
  {
   "name": "roles/external/meta",
   "ftype": "dir",
   "chksum_type": null,
   "chksum_sha256": null,
   "format": 1
  },
  {
   "name": "roles/external/meta/main.yml",
   "ftype": "file",
   "chksum_type": "sha256",
   "chksum_sha256": "e82c60136cb1895d61432dd52c83d4c6e8ad4c654a697ac2d5b5e4a288866d87",
   "format": 1
  },
  {
   "name": "roles/external/tasks",
   "ftype": "dir",
   "chksum_type": null,
   "chksum_sha256": null,
   "format": 1
  },
  {
   "name": "roles/external/tasks/main.yml",
   "ftype": "file",
   "chksum_type": "sha256",
   "chksum_sha256": "48b2826242cb9a3aa5a8f81d8d0016bad17515ecda49f0ac66012e323fd3464f",
   "format": 1
  },
  {
   "name": "roles/external/templates",
   "ftype": "dir",
   "chksum_type": null,
   "chksum_sha256": null,
   "format": 1
  },
  {
   "name": "roles/external/tests",
   "ftype": "dir",
   "chksum_type": null,
   "chksum_sha256": null,
   "format": 1
  },
  {
   "name": "roles/external/tests/inventory",
   "ftype": "file",
   "chksum_type": "sha256",
   "chksum_sha256": "e02233819b1a09844410549191813f7cc7ba360f21298578f4ba1727a27d87fc",
   "format": 1
  },
  {
   "name": "roles/external/tests/test.yml",
   "ftype": "file",
   "chksum_type": "sha256",
   "chksum_sha256": "79efab872a28701d239b014653d72f113f7a282b75954322043e7640e7d1fd0c",
   "format": 1
  },
  {
   "name": "roles/external/vars",
   "ftype": "dir",
   "chksum_type": null,
   "chksum_sha256": null,
   "format": 1
  },
  {
   "name": "roles/external/vars/main.yml",
   "ftype": "file",
   "chksum_type": "sha256",
   "chksum_sha256": "c2a383616aa04abae76fbd82eace34589f272677043c856f84ffd4bd5dcf1ff8",
   "format": 1
  },
  {
   "name": "roles/external/.travis.yml",
   "ftype": "file",
   "chksum_type": "sha256",
   "chksum_sha256": "43e63a93716f15cdb102c201e4631be604b45910b8c749c78d89e3fc076c7c7e",
   "format": 1
  },
  {
   "name": "roles/external/README.md",
   "ftype": "file",
   "chksum_type": "sha256",
   "chksum_sha256": "cc751d75266f757a38189f15d54e548dc87706f14a39756995c27b49eaca8a07",
   "format": 1
  },
  {
   "name": "roles/external/defaults",
   "ftype": "dir",
   "chksum_type": null,
   "chksum_sha256": null,
   "format": 1
  },
  {
   "name": "roles/external/defaults/main.yml",
   "ftype": "file",
   "chksum_type": "sha256",
   "chksum_sha256": "dd1ce2d59a5a0606a91d9cd62cc3d8e7d44b9f603d414f0c0232862380567371",
   "format": 1
  },
  {
   "name": "roles/print",
   "ftype": "dir",
   "chksum_type": null,
   "chksum_sha256": null,
   "format": 1
  },
  {
   "name": "roles/print/handlers",
   "ftype": "dir",
   "chksum_type": null,
   "chksum_sha256": null,
   "format": 1
  },
  {
   "name": "roles/print/handlers/main.yml",
   "ftype": "file",
   "chksum_type": "sha256",
   "chksum_sha256": "04448c8ced306ebde339cc7e7b4c2dee14933b9bc7ad0ddedeac527c0e66e089",
   "format": 1
  },
  {
   "name": "roles/print/meta",
   "ftype": "dir",
   "chksum_type": null,
   "chksum_sha256": null,
   "format": 1
  },
  {
   "name": "roles/print/meta/main.yml",
   "ftype": "file",
   "chksum_type": "sha256",
   "chksum_sha256": "e82c60136cb1895d61432dd52c83d4c6e8ad4c654a697ac2d5b5e4a288866d87",
   "format": 1
  },
  {
   "name": "roles/print/tasks",
   "ftype": "dir",
   "chksum_type": null,
   "chksum_sha256": null,
   "format": 1
  },
  {
   "name": "roles/print/tasks/main.yml",
   "ftype": "file",
   "chksum_type": "sha256",
   "chksum_sha256": "0c4886b477093a03227f75963ae8fac4b32c4b9b2a98503ba05f1057c50cbf51",
   "format": 1
  },
  {
   "name": "roles/print/templates",
   "ftype": "dir",
   "chksum_type": null,
   "chksum_sha256": null,
   "format": 1
  },
  {
   "name": "roles/print/vars",
   "ftype": "dir",
   "chksum_type": null,
   "chksum_sha256": null,
   "format": 1
  },
  {
   "name": "roles/print/vars/main.yml",
   "ftype": "file",
   "chksum_type": "sha256",
   "chksum_sha256": "3f7ccd0b80eaf1b481586e8828d340adeeab9a4eee0be7234a9fd398030aa569",
   "format": 1
  },
  {
   "name": "roles/print/.travis.yml",
   "ftype": "file",
   "chksum_type": "sha256",
   "chksum_sha256": "43e63a93716f15cdb102c201e4631be604b45910b8c749c78d89e3fc076c7c7e",
   "format": 1
  },
  {
   "name": "roles/print/README.md",
   "ftype": "file",
   "chksum_type": "sha256",
   "chksum_sha256": "cc751d75266f757a38189f15d54e548dc87706f14a39756995c27b49eaca8a07",
   "format": 1
  },
  {
   "name": "roles/print/defaults",
   "ftype": "dir",
   "chksum_type": null,
   "chksum_sha256": null,
   "format": 1
  },
  {
   "name": "roles/print/defaults/main.yml",
   "ftype": "file",
   "chksum_type": "sha256",
   "chksum_sha256": "51b9ce0be43abc289dc7f298947127efb1227f641946ed1215c945ce5abd369c",
   "format": 1
  },
  {
   "name": "roles/security_server",
   "ftype": "dir",
   "chksum_type": null,
   "chksum_sha256": null,
   "format": 1
  },
  {
   "name": "roles/security_server/tasks",
   "ftype": "dir",
   "chksum_type": null,
   "chksum_sha256": null,
   "format": 1
  },
  {
   "name": "roles/security_server/tasks/main.yml",
   "ftype": "file",
   "chksum_type": "sha256",
   "chksum_sha256": "7ad2647d9ed3765fc75ef404d772826da996903f263cc0bc6805a6acabaf6d0e",
   "format": 1
  },
  {
   "name": "roles/security_server/templates",
   "ftype": "dir",
   "chksum_type": null,
   "chksum_sha256": null,
   "format": 1
  },
  {
   "name": "roles/security_server/tests",
   "ftype": "dir",
   "chksum_type": null,
   "chksum_sha256": null,
   "format": 1
  },
  {
   "name": "roles/security_server/tests/inventory",
   "ftype": "file",
   "chksum_type": "sha256",
   "chksum_sha256": "e02233819b1a09844410549191813f7cc7ba360f21298578f4ba1727a27d87fc",
   "format": 1
  },
  {
   "name": "roles/security_server/tests/test.yml",
   "ftype": "file",
   "chksum_type": "sha256",
   "chksum_sha256": "43f0af4bc5da8431911c6dd7c2c8ca8be34b348d2418415be7ac071b8723d40a",
   "format": 1
  },
  {
   "name": "roles/security_server/vars",
   "ftype": "dir",
   "chksum_type": null,
   "chksum_sha256": null,
   "format": 1
  },
  {
   "name": "roles/security_server/vars/main.yml",
   "ftype": "file",
   "chksum_type": "sha256",
   "chksum_sha256": "2e2f7e1fc0e5223032d62f44aad68231e3d29f91b988d4db3e5105e30d25da25",
   "format": 1
  },
  {
   "name": "roles/security_server/.travis.yml",
   "ftype": "file",
   "chksum_type": "sha256",
   "chksum_sha256": "43e63a93716f15cdb102c201e4631be604b45910b8c749c78d89e3fc076c7c7e",
   "format": 1
  },
  {
   "name": "roles/security_server/README.md",
   "ftype": "file",
   "chksum_type": "sha256",
   "chksum_sha256": "cc751d75266f757a38189f15d54e548dc87706f14a39756995c27b49eaca8a07",
   "format": 1
  },
  {
   "name": "roles/security_server/defaults",
   "ftype": "dir",
   "chksum_type": null,
   "chksum_sha256": null,
   "format": 1
  },
  {
   "name": "roles/security_server/defaults/main.yml",
   "ftype": "file",
   "chksum_type": "sha256",
   "chksum_sha256": "e7279ee38f55cd6ef366e507a8be4a67adbb0382719772a4f27832ba568703a1",
   "format": 1
  },
  {
   "name": "roles/security_server/files",
   "ftype": "dir",
   "chksum_type": null,
   "chksum_sha256": null,
   "format": 1
  },
  {
   "name": "roles/security_server/handlers",
   "ftype": "dir",
   "chksum_type": null,
   "chksum_sha256": null,
   "format": 1
  },
  {
   "name": "roles/security_server/handlers/main.yml",
   "ftype": "file",
   "chksum_type": "sha256",
   "chksum_sha256": "771ae72044e559813cc175420228ea8159d311e43a8f10836df6d8a4cb3d2156",
   "format": 1
  },
  {
   "name": "roles/security_server/meta",
   "ftype": "dir",
   "chksum_type": null,
   "chksum_sha256": null,
   "format": 1
  },
  {
   "name": "roles/security_server/meta/main.yml",
   "ftype": "file",
   "chksum_type": "sha256",
   "chksum_sha256": "e82c60136cb1895d61432dd52c83d4c6e8ad4c654a697ac2d5b5e4a288866d87",
   "format": 1
  },
  {
   "name": "roles/web_server",
   "ftype": "dir",
   "chksum_type": null,
   "chksum_sha256": null,
   "format": 1
  },
  {
   "name": "roles/web_server/files",
   "ftype": "dir",
   "chksum_type": null,
   "chksum_sha256": null,
   "format": 1
  },
  {
   "name": "roles/web_server/handlers",
   "ftype": "dir",
   "chksum_type": null,
   "chksum_sha256": null,
   "format": 1
  },
  {
   "name": "roles/web_server/handlers/main.yml",
   "ftype": "file",
   "chksum_type": "sha256",
   "chksum_sha256": "eecab81f86feb9b6d04ee56084fae38771cb47f3a35df56f955094a13d0753c9",
   "format": 1
  },
  {
   "name": "roles/web_server/meta",
   "ftype": "dir",
   "chksum_type": null,
   "chksum_sha256": null,
   "format": 1
  },
  {
   "name": "roles/web_server/meta/main.yml",
   "ftype": "file",
   "chksum_type": "sha256",
   "chksum_sha256": "52825ca52734b0a2d50ae313bd7e9998a2df996e4fccf2747cd965d6efdcd0fd",
   "format": 1
  },
  {
   "name": "roles/web_server/tasks",
   "ftype": "dir",
   "chksum_type": null,
   "chksum_sha256": null,
   "format": 1
  },
  {
   "name": "roles/web_server/tasks/main.yml",
   "ftype": "file",
   "chksum_type": "sha256",
   "chksum_sha256": "4dbcf048ac18ef3119b9f89b1f090d0fab45cfe45c14332d2cd67db30cfd1aa7",
   "format": 1
  },
  {
   "name": "roles/web_server/templates",
   "ftype": "dir",
   "chksum_type": null,
   "chksum_sha256": null,
   "format": 1
  },
  {
   "name": "roles/web_server/templates/stat.j2",
   "ftype": "file",
   "chksum_type": "sha256",
   "chksum_sha256": "2be2fc914d5d38534efaa064099843cdf5908854e9c82aeeda457419196a5284",
   "format": 1
  },
  {
   "name": "roles/web_server/tests",
   "ftype": "dir",
   "chksum_type": null,
   "chksum_sha256": null,
   "format": 1
  },
  {
   "name": "roles/web_server/tests/inventory",
   "ftype": "file",
   "chksum_type": "sha256",
   "chksum_sha256": "e02233819b1a09844410549191813f7cc7ba360f21298578f4ba1727a27d87fc",
   "format": 1
  },
  {
   "name": "roles/web_server/tests/test.yml",
   "ftype": "file",
   "chksum_type": "sha256",
   "chksum_sha256": "ca44ac9f851179a836bb27f44084b1b9c898ccd24493209213ff323ca80c9a3b",
   "format": 1
  },
  {
   "name": "roles/web_server/vars",
   "ftype": "dir",
   "chksum_type": null,
   "chksum_sha256": null,
   "format": 1
  },
  {
   "name": "roles/web_server/vars/main.yml",
   "ftype": "file",
   "chksum_type": "sha256",
   "chksum_sha256": "7b0c5948b1f835968ff1a91b0d6755298410d1d3adafca2d2b05e19520245460",
   "format": 1
  },
  {
   "name": "roles/web_server/.travis.yml",
   "ftype": "file",
   "chksum_type": "sha256",
   "chksum_sha256": "43e63a93716f15cdb102c201e4631be604b45910b8c749c78d89e3fc076c7c7e",
   "format": 1
  },
  {
   "name": "roles/web_server/README.md",
   "ftype": "file",
   "chksum_type": "sha256",
   "chksum_sha256": "cc751d75266f757a38189f15d54e548dc87706f14a39756995c27b49eaca8a07",
   "format": 1
  },
  {
   "name": "roles/web_server/defaults",
   "ftype": "dir",
   "chksum_type": null,
   "chksum_sha256": null,
   "format": 1
  },
  {
   "name": "roles/web_server/defaults/main.yml",
   "ftype": "file",
   "chksum_type": "sha256",
   "chksum_sha256": "616b7f0d523e9f806a6ca4afc4fe323869eeb16d6c8d66aefcbc113743985fd1",
   "format": 1
  },
  {
   "name": "meta",
   "ftype": "dir",
   "chksum_type": null,
   "chksum_sha256": null,
   "format": 1
  },
  {
   "name": "meta/runtime.yml",
   "ftype": "file",
   "chksum_type": "sha256",
   "chksum_sha256": "bf6223153f567af542389964af93ed3bf3c430a0793d0469181fefbf16cd08f9",
   "format": 1
  }
 ],
 "format": 1
}